{
  "code": "200",
  "msg": "success",
  "data": [
    {
      "time": 2,
      "date": "2017年3月",
      "data": [
        {
          "name": "信访编号",
          "value": "LF132019121219173"
        },
        {
          "name": "信访目的",
          "value": "揭发控告"
        },
        {
          "name": "信访时间",
          "value": "2017年3月"
        },
        {
          "name": "问题属地",
          "value": "河北省邯郸市"
        },
        {
          "name": "内容分类",
          "value": "城乡建设-国有土地城乡建设-国有土地"
        },
        {
          "name": "登记单位",
          "value": "投诉办三处/投诉受理投诉办三处/投诉受理"
        },
        {
          "name": "信访形式",
          "value": "网上投诉"
        },
        {
          "name": "信访状态",
          "value": "已作出处理意见"
        }
      ]
    },
    {
      "time": 4,
      "date": "2019年9月",
      "data": [
        {
          "name": "信访编号",
          "value": "LF132019121219173"
        },
        {
          "name": "信访目的",
          "value": "揭发控告"
        },
        {
          "name": "信访时间",
          "value": "2019年9月"
        },
        {
          "name": "问题属地",
          "value": "河北省邯郸市"
        },
        {
          "name": "内容分类",
          "value": "城乡建设-国有土地城乡建设-国有土地"
        },
        {
          "name": "登记单位",
          "value": "投诉办三处/投诉受理投诉办三处/投诉受理"
        },
        {
          "name": "信访形式",
          "value": "网上投诉"
        },
        {
          "name": "信访状态",
          "value": "已作出处理意见"
        }
      ]
    },
    {
      "time": 2,
      "date": "2020年1月",
      "data": [
        {
          "name": "信访编号",
          "value": "LF132019121219173"
        },
        {
          "name": "信访目的",
          "value": "揭发控告"
        },
        {
          "name": "信访时间",
          "value": "2020年1月"
        },
        {
          "name": "问题属地",
          "value": "河北省邯郸市"
        },
        {
          "name": "内容分类",
          "value": "城乡建设-国有土地城乡建设-国有土地"
        },
        {
          "name": "登记单位",
          "value": "投诉办三处/投诉受理投诉办三处/投诉受理"
        },
        {
          "name": "信访形式",
          "value": "网上投诉"
        },
        {
          "name": "信访状态",
          "value": "已作出处理意见"
        }
      ]
    },
    {
      "time": 6,
      "date": "2020年3月",
      "data": [
        {
          "name": "信访编号",
          "value": "LF132019121219173"
        },
        {
          "name": "信访目的",
          "value": "揭发控告"
        },
        {
          "name": "信访时间",
          "value": "2020年3月15日"
        },
        {
          "name": "问题属地",
          "value": "河北省邯郸市"
        },
        {
          "name": "内容分类",
          "value": "城乡建设-国有土地城乡建设-国有土地"
        },
        {
          "name": "登记单位",
          "value": "投诉办三处/投诉受理投诉办三处/投诉受理"
        },
        {
          "name": "信访形式",
          "value": "网上投诉"
        },
        {
          "name": "信访状态",
          "value": "已作出处理意见"
        }
      ]
    }
  ]
}
