{
  "code": "200",
  "msg": "success",
  "map": {
    "value_g0_1": "房地产开发管理",
    "value_g1_1": "物业服务",
    "value_g2_1": "保证性住房",
    "value_g3_1": "产权交易",
    "value_g4_1": "住房公积金"
  },
  "data":[
    {
      "name": "1",
      "value_g0_1": 22,
      "value_g1_1": 70,
      "value_g2_1": 18,
      "value_g3_1": 4,
      "value_g4_1": 4
    },
    {
      "name": "2",
      "value_g0_1": 3,
      "value_g1_1": 33,
      "value_g2_1": 94,
      "value_g3_1": 62,
      "value_g4_1": 4
    },
    {
      "name": "3",
      "value_g0_1": 34,
      "value_g1_1": 69,
      "value_g2_1": 88,
      "value_g3_1": 43,
      "value_g4_1": 4
    },
    {
      "name": "4",
      "value_g0_1": 36,
      "value_g1_1": 36,
      "value_g2_1": 49,
      "value_g3_1": 90,
      "value_g4_1": 4
    },
    {
      "name": "5",
      "value_g0_1": 24,
      "value_g1_1": 43,
      "value_g2_1": 81,
      "value_g3_1": 32,
      "value_g4_1": 4
    },
    {
      "name": "6",
      "value_g0_1": 32,
      "value_g1_1": 51,
      "value_g2_1": 71,
      "value_g3_1": 69,
      "value_g4_1": 4
    },
    {
      "name": "7",
      "value_g0_1": 10,
      "value_g1_1": 76,
      "value_g2_1": 41,
      "value_g3_1": 94,
      "value_g4_1": 4
    },
    {
      "name": "8",
      "value_g0_1": 43,
      "value_g1_1": 57,
      "value_g2_1": 80,
      "value_g3_1": 5,
      "value_g4_1": 4
    },
    {
      "name": "9",
      "value_g0_1": 100,
      "value_g1_1": 5,
      "value_g2_1": 99,
      "value_g3_1": 10,
      "value_g4_1": 4
    },
    {
      "name": "10",
      "value_g0_1": 71,
      "value_g1_1": 27,
      "value_g2_1": 71,
      "value_g3_1": 97,
      "value_g4_1": 4
    },
    {
      "name": "11",
      "value_g0_1": 57,
      "value_g1_1": 19,
      "value_g2_1": 41,
      "value_g3_1": 79,
      "value_g4_1": 4
    },
    {
      "name": "12",
      "value_g0_1": 5,
      "value_g1_1": 28,
      "value_g2_1": 77,
      "value_g3_1": 91,
      "value_g4_1": 4
    }
  ]
}
